mingaleg_lib/__init__.py
mingaleg_lib/py.typed
mingaleg_lib/version.py
mingaleg_lib/secrets/__init__.py
mingaleg_lib/secrets/encrypt.py
mingaleg_lib/secrets/file_system.py
mingaleg_lib/secrets/encrypted/github-ci.bin
mingaleg_lib/secrets/encrypted/osx-omin-m2.bin
mingaleg_lib/secrets/encrypted/recovery.bin
mingaleg_lib/secrets/public_keyring/github-ci.pem
mingaleg_lib/secrets/public_keyring/osx-omin-m2.pem
mingaleg_lib/secrets/public_keyring/recovery.pem
mingaleg_lib-0.2.0.dist-info/licenses/LICENSE
mingaleg_lib-0.2.0.dist-info/METADATA
mingaleg_lib-0.2.0.dist-info/WHEEL
mingaleg_lib-0.2.0.dist-info/top_level.txt
mingaleg_lib-0.2.0.dist-info/RECORD
