Metadata-Version: 2.4
Name: mingaleg-lib
Version: 0.2.0
Author-email: Allen Institute for Artificial Intelligence <contact@allenai.org>
License:                                  Apache License
Project-URL: Homepage, https://github.com/mingaleg/mingaleg_lib
Project-URL: Repository, https://github.com/mingaleg/mingaleg_lib
Project-URL: Changelog, https://github.com/mingaleg/mingaleg_lib/blob/main/CHANGELOG.md
Classifier: Intended Audience :: Science/Research
Classifier: Development Status :: 3 - Alpha
Classifier: License :: OSI Approved :: Apache Software License
Classifier: Programming Language :: Python :: 3
Classifier: Topic :: Scientific/Engineering :: Artificial Intelligence
Requires-Python: >=3.9
License-File: LICENSE
Requires-Dist: pycryptodome>=3.22.0
Requires-Dist: python-dotenv>=1.1.0
Provides-Extra: dev
Requires-Dist: ruff; extra == "dev"
Requires-Dist: mypy<2.0,>=1.0; extra == "dev"
Requires-Dist: black<25.0,>=23.0; extra == "dev"
Requires-Dist: isort<5.14,>=5.12; extra == "dev"
Requires-Dist: pytest; extra == "dev"
Requires-Dist: pytest-sphinx; extra == "dev"
Requires-Dist: pytest-cov; extra == "dev"
Requires-Dist: twine>=1.11.0; extra == "dev"
Requires-Dist: build; extra == "dev"
Requires-Dist: setuptools; extra == "dev"
Requires-Dist: wheel; extra == "dev"
Requires-Dist: Sphinx<9.0,>=6.0; extra == "dev"
Requires-Dist: furo==2024.8.6; extra == "dev"
Requires-Dist: myst-parser>=1.0; extra == "dev"
Requires-Dist: sphinx-copybutton; extra == "dev"
Requires-Dist: sphinx-autobuild; extra == "dev"
Requires-Dist: sphinx-autodoc-typehints==1.23.3; extra == "dev"
Requires-Dist: packaging; extra == "dev"
Dynamic: license-file
